fast_dynamodb_json/__init__.py
fast_dynamodb_json/_version.py
fast_dynamodb_json/api.py
fast_dynamodb_json/deserialize.py
fast_dynamodb_json/paths.py
fast_dynamodb_json/schema.py
fast_dynamodb_json/sentinel.py
fast_dynamodb_json/serialize.py
fast_dynamodb_json/typehint.py
fast_dynamodb_json/docs/__init__.py
fast_dynamodb_json/tests/__init__.py
fast_dynamodb_json/tests/case.py
fast_dynamodb_json/tests/helper.py
fast_dynamodb_json/vendor/__init__.py
fast_dynamodb_json/vendor/polars_utils.py
fast_dynamodb_json/vendor/pytest_cov_helper.py
fast_dynamodb_json/vendor/timer.py
fast_dynamodb_json-0.1.1.dist-info/AUTHORS.rst
fast_dynamodb_json-0.1.1.dist-info/LICENSE.txt
fast_dynamodb_json-0.1.1.dist-info/METADATA
fast_dynamodb_json-0.1.1.dist-info/WHEEL
fast_dynamodb_json-0.1.1.dist-info/top_level.txt
fast_dynamodb_json-0.1.1.dist-info/RECORD
